{
  "_fv": 39,
  "_type": "tool",
  "definition": {
    "renderType": 0,
    "texture": "unnamed",
    "customModelName": "Normal",
    "name": "Marreta Do Zoio",
    "specialInfo": [],
    "creativeTab": {
      "value": "TOOLS"
    },
    "toolType": "Pickaxe",
    "harvestLevel": 6,
    "efficiency": 13.0,
    "attackSpeed": 1.0,
    "enchantability": 42,
    "damageVsEntity": 7.1,
    "usageCount": 2164,
    "blocksAffected": [],
    "hasGlow": false,
    "repairItems": [
      {
        "value": "CUSTOM:KoronbekiIngot"
      }
    ],
    "immuneToFire": false,
    "stayInGridWhenCrafting": false,
    "damageOnCrafting": false,
    "onBlockDestroyedWithTool": {
      "name": "Marretazoio"
    }
  }
}